{
  "Alexander - The Cuff of the Father": [
    "Gordian Footman"
  ],
  "Alexander - The Fist of the Father": [
    "Faust"
  ],
  "Cape Westwind": [
    "Rhitahtyn Sas Arvina"
  ],
  "Castrum Fluminis": [
    "Tsukuyomi"
  ],
  "Castrum Marinum": [
    "The Emerald Weapon"
  ],
  "Castrum Marinum (Extreme)": [
    "The Emerald Weapon"
  ],
  "Cinder Drift": [
    "The Ruby Weapon"
  ],
  "Containment Bay P1T6 (Extreme)": [
    "Sophia"
  ],
  "Containment Bay S1T7 (Extreme)": [
    "Sephirot"
  ],
  "Containment Bay Z1T9 (Extreme)": [
    "Zurvan"
  ],
  "Deltascape V4.0 (Savage)": [
    "Exdeath"
  ],
  "Eden's Gate: Descent": [
    "Voidwalker"
  ],
  "Eden's Gate: Descent (Savage)": [
    "Voidwalker"
  ],
  "Eden's Gate: Inundation": [
    "Leviathan"
  ],
  "Eden's Gate: Inundation (Savage)": [
    "Leviathan"
  ],
  "Eden's Gate: Resurrection": [
    "Eden Prime"
  ],
  "Eden's Gate: Resurrection (Savage)": [
    "Eden Prime"
  ],
  "Eden's Gate: Sepulture": [
    "Titan"
  ],
  "Eden's Gate: Sepulture (Savage)": [
    "Titan"
  ],
  "Eden's Promise: Anamorphosis": [
    "Fatebreaker"
  ],
  "Eden's Promise: Anamorphosis (Savage)": [
    "Fatebreaker"
  ],
  "Eden's Promise: Eternity": [
    "Eden's Promise"
  ],
  "Eden's Promise: Eternity (Savage)": [
    "Eden's Promise"
  ],
  "Eden's Promise: Litany": [
    "Shadowkeeper"
  ],
  "Eden's Promise: Litany (Savage)": [
    "Shadowkeeper"
  ],
  "Eden's Promise: Umbra": [
    "Cloud Of Darkness"
  ],
  "Eden's Promise: Umbra (Savage)": [
    "Cloud Of Darkness"
  ],
  "Eden's Verse: Fulmination": [
    "Ramuh"
  ],
  "Eden's Verse: Fulmination (Savage)": [
    "Ramuh"
  ],
  "Eden's Verse: Furor": [
    "Garuda"
  ],
  "Eden's Verse: Furor (Savage)": [
    "Garuda"
  ],
  "Eden's Verse: Iconoclasm": [
    "The Idol Of Darkness"
  ],
  "Eden's Verse: Iconoclasm (Savage)": [
    "The Idol Of Darkness"
  ],
  "Eden's Verse: Refulgence": [
    "Shiva"
  ],
  "Eden's Verse: Refulgence (Savage)": [
    "Shiva"
  ],
  "Emanation": [
    "Dreaming Kshatriya"
  ],
  "Memoria Misera (Extreme)": [
    "Varis Yae Galvus"
  ],
  "Sigmascape V4.0 (Savage)": [
    "Kefka"
  ],
  "Syrcus Tower": [
    "Shinobi"
  ],
  "The Cloud Deck (Extreme)": [
    "The Diamond Weapon"
  ],
  "The Copied Factory": [
    "Serial-Jointed Command Model"
  ],
  "The Crown of the Immaculate": [
    "Innocence"
  ],
  "The Dancing Plague": [
    "Mustardseed"
  ],
  "The Dying Gasp": [
    "Hades"
  ],
  "The Epic of Alexander (Ultimate)": [
    "Living Liquid"
  ],
  "The Minstrel's Ballad: Hades's Elegy": [
    "Hades"
  ],
  "The Tower at Paradigm's Breach": [
    "Knave Of Hearts"
  ],
  "Thok ast Thok (Extreme)": [
    "Ravana"
  ],
  "Thok ast Thok (Hard)": [
    "Ravana"
  ],
  "Thornmarch (Hard)": [
    "Whiskerwall Kupdi Koop"
  ],
  "the Bowl of Embers": [
    "Infernal Nail"
  ],
  "the Bowl of Embers (Hard)": [
    "Ifrit"
  ],
  "the Chrysalis": [
    "Nabriales"
  ],
  "the Crown of the Immaculate (Extreme)": [
    "Innocence"
  ],
  "the Dancing Plague (Extreme)": [
    "Titania"
  ],
  "the Final Steps of Faith": [
    "Nidhogg"
  ],
  "the Great Hunt": [
    "Rathalos"
  ],
  "the Great Hunt (Extreme)": [
    "Rathalos"
  ],
  "the Howling Eye": [
    "Garuda"
  ],
  "the Howling Eye (Hard)": [
    "Garuda"
  ],
  "the Labyrinth of the Ancients": [
    "Earth Homunculus"
  ],
  "the Limitless Blue (Extreme)": [
    "Vuk'maii Vundu"
  ],
  "the Limitless Blue (Hard)": [
    "Vuk'maii Vundu"
  ],
  "the Minstrel's Ballad: Nidhogg's Rage": [
    "Nidhogg"
  ],
  "the Minstrel's Ballad: Thordan's Reign": [
    "King Thordan"
  ],
  "the Minstrel's Ballad: Tsukuyomi's Pain": [
    "Tsukuyomi"
  ],
  "the Navel": [
    "Titan"
  ],
  "the Navel (Hard)": [
    "Titan"
  ],
  "the Orbonne Monastery": [
    "Harpy"
  ],
  "the Pool of Tribute": [
    "Susano"
  ],
  "the Puppets' Bunker": [
    "813P-Operated Aegis Unit"
  ],
  "the Ridorana Lighthouse": [
    "Famfrit, The Darkening Cloud"
  ],
  "the Royal City of Rabanastre": [
    "Mateus, The Corrupt"
  ],
  "the Royal Menagerie": [
    "Shinryu"
  ],
  "the Seat of Sacrifice": [
    "Warrior Of Light"
  ],
  "the Singularity Reactor": [
    "King Thordan"
  ],
  "the Steps of Faith": [
    "Vishap"
  ],
  "the Striking Tree (Hard)": [
    "Grey Arbiter"
  ],
  "the Unending Coil of Bahamut (Ultimate)": [
    "Twintania"
  ],
  "the Weapon's Refrain (Ultimate)": [
    "Garuda"
  ],
  "the Whorleater (Hard)": [
    "Leviathan"
  ],
  "the World of Darkness": [
    "Garm"
  ]
}